socialname/__init__.py
socialname/__main__.py
socialname/__version__.py
socialname/notify.py
socialname/output.py
socialname/result.py
socialname/sites.py
socialname/sites_load.py
socialname/socialname.py
socialname/cli/__init__.py
socialname/cli/args.py
socialname/cli/command.py
socialname/logics/__init__.py
socialname/logics/_base.py
socialname/logics/_base_simple_request.py
socialname/logics/message.py
socialname/logics/response_url.py
socialname/logics/status_code.py
socialname/resources/data.json
socialname-0.1.3.dist-info/LICENSE
socialname-0.1.3.dist-info/METADATA
socialname-0.1.3.dist-info/WHEEL
socialname-0.1.3.dist-info/entry_points.txt
socialname-0.1.3.dist-info/top_level.txt
socialname-0.1.3.dist-info/RECORD
