Metadata-Version: 2.1
Name: socialname
Version: 0.1.3
Summary: Find username across social network sites
Home-page: https://github.com/yhay81/socialname
Author: Yusuke Hayashi
Author-email: yusuke8h@gmail.com
License: MIT
Project-URL: Source, https://github.com/yhay81/socialname
Keywords: sns
Platform: UNKNOWN
Classifier: Development Status :: 3 - Alpha
Classifier: Intended Audience :: Developers
Classifier: Intended Audience :: End Users/Desktop
Classifier: Natural Language :: English
Classifier: License :: OSI Approved :: MIT License
Classifier: Programming Language :: Python
Classifier: Programming Language :: Python :: 3
Classifier: Programming Language :: Python :: 3.7
Classifier: Programming Language :: Python :: 3.8
Classifier: Programming Language :: Python :: 3.9
Classifier: Programming Language :: Python :: Implementation :: CPython
Classifier: Programming Language :: Python :: Implementation :: PyPy
Requires-Python: >=3.6
Requires-Dist: Cerberus (>=1.3.2)
Requires-Dist: colorama (>=0.4.4)
Requires-Dist: requests (>=2.25.1)
Requires-Dist: torrequest (>=0.1.0)
Requires-Dist: psutil (>=5.8.0)
